[
  {
    "name": "Autonomous Rate Manager",
    "url": "https://www.liquity.org/blog/autonomous-interest-manager",
    "strategies": [
      {
        "name": "",
        "address": "0xe507e4d0763851a6287238aadd243948d18ab60a",
        "branches": ["ETH"]
      }
    ]
  },
  {
    "name": "Autonomous Rate Manager",
    "url": "https://www.liquity.org/blog/autonomous-interest-manager",
    "strategies": [
      {
        "name": "",
        "address": "0x8869a6fb59a8df330f90d9fbf46ebfaff6d4bc14",
        "branches": ["wstETH"]
      }
    ]
  },
  {
    "name": "Autonomous Rate Manager",
    "url": "https://www.liquity.org/blog/autonomous-interest-manager",
    "strategies": [
      {
        "name": "",
        "address": "0x7700b2d305f47ae82e9598bab6d7ccb57299a82b",
        "branches": ["rETH"]
      }
    ]
  },
  {
    "name": "Summerstone",
    "url": "https://summerstone.xyz/docs/for-users/managed-interest-rates/supported-protocols/bold-from-liquity-v2/index.html#active-strategies",
    "strategies": [
      {
        "name": "Balanced",
        "address": "0x00000000001991cee928c561e37725816cbf73ba",
        "branches": ["ETH"]
      },
      {
        "name": "Balanced",
        "address": "0x000000000017d2a7b863e9ebbe6f9ab7255eb7c5",
        "branches": ["wstETH"]
      },
      {
        "name": "Balanced",
        "address": "0x0000000000704f94ce2fe636dab92677a9745dc3",
        "branches": ["rETH"]
      }
    ]
  },
  {
    "name": "Trove Zero",
    "url": "https://trovezero.xyz/",
    "strategies": [
      {
        "name": "",
        "address": "0xe707784292289be3aa0fb6f9d33d420291f98695",
        "branches": ["wstETH"]
      }
    ]
  },
  {
    "name": "Bolder Cash",
    "url": "https://bolder.cash/rate-strategies?f=bold&c=combined",
    "strategies": [
      {
        "name": "Low Rate",
        "address": "0x25bc0272217fb0fd7a2ff0d62cebe1aba15e4d91",
        "branches": ["ETH", "wstETH", "rETH"]
      },
      {
        "name": "Mid Rate",
        "address": "0x50bc02c6c7124e6e1b8333b80a0416e504e2d044",
        "branches": ["ETH", "wstETH", "rETH"]
      },
      {
        "name": "High Rate",
        "address": "0x75bc02022344159b7ef50a3ff5291dd2bc6918c7",
        "branches": ["ETH", "wstETH", "rETH"]
      }
    ]
  }
]
